pydanmaku/__init__.py
pydanmaku/bullet.py
pydanmaku/game.py
pydanmaku/pdobject.py
pydanmaku/player.py
pydanmaku/utils.py
pydanmaku-0.0.0a0.dist-info/DESCRIPTION.rst
pydanmaku-0.0.0a0.dist-info/METADATA
pydanmaku-0.0.0a0.dist-info/RECORD
pydanmaku-0.0.0a0.dist-info/WHEEL
pydanmaku-0.0.0a0.dist-info/metadata.json
pydanmaku-0.0.0a0.dist-info/top_level.txt
