Metadata-Version: 2.0
Name: pydanmaku
Version: 0.0.0a0
Summary: A Danmaku engine written in python
Home-page: https://github.com/hanss314/PyDanmaku
Author: hanss314
Author-email: UNKNOWN
License: MIT
Platform: UNKNOWN
Requires-Dist: pygame
